prynth/__init__.py
prynth-1.1.0.dist-info/METADATA
prynth-1.1.0.dist-info/WHEEL
prynth-1.1.0.dist-info/top_level.txt
prynth-1.1.0.dist-info/RECORD
