Metadata-Version: 2.1
Name: prynth
Version: 1.1.0
Summary: Prynth allows you to print a text with coordinates.
Home-page: https://github.com/lactua/prynth
Author: Lactua
Author-email: minedrayxio@gmail.com
Project-URL: Bug Tracker, https://github.com/lactua/prynth/issues
Classifier: Programming Language :: Python :: 3
Classifier: License :: OSI Approved :: MIT License
Classifier: Operating System :: OS Independent
Requires-Python: >=3.6
